fansile666/__init__.py
fansile666/core.py
fansile666-0.1.0.dist-info/LICENCE.txt
fansile666-0.1.0.dist-info/METADATA
fansile666-0.1.0.dist-info/WHEEL
fansile666-0.1.0.dist-info/top_level.txt
fansile666-0.1.0.dist-info/RECORD
